examples/__init__.py
examples/my_first_infertrade_strategy.py
infertrade/PandasEnum.py
infertrade/__init__.py
infertrade/_version.py
infertrade/api.py
infertrade/base.py
infertrade/algos/__init__.py
infertrade/algos/community/__init__.py
infertrade/algos/community/allocations.py
infertrade/algos/community/permalinks.py
infertrade/algos/community/signals.py
infertrade/algos/external/__init__.py
infertrade/algos/external/ta.py
infertrade/algos/external/ta_regressions.py
infertrade/data/__init__.py
infertrade/data/simulate_data.py
infertrade/utilities/__init__.py
infertrade/utilities/api_automation.py
infertrade/utilities/export.py
infertrade/utilities/operations.py
infertrade/utilities/performance.py
infertrade/utilities/simple_functions.py
infertrade-0.0.62.dist-info/LICENSE
infertrade-0.0.62.dist-info/METADATA
infertrade-0.0.62.dist-info/WHEEL
infertrade-0.0.62.dist-info/top_level.txt
infertrade-0.0.62.dist-info/RECORD
