Metadata-Version: 2.1
Name: infertrade
Version: 0.0.62
Summary: Pandas and SciKit Learn compatible open source interface for algorithmic trading functions.
Home-page: https://github.com/ta-oliver/infertrade
Author: Thomas Oliver
Author-email: support@infertrade.com
License: Apache License 2.0
Platform: UNKNOWN
Classifier: License :: OSI Approved :: Apache Software License
Classifier: Development Status :: 2 - Pre-Alpha
Classifier: Programming Language :: Python
Classifier: Programming Language :: Python :: 3
Classifier: Programming Language :: Python :: 3.7
Classifier: Operating System :: OS Independent
Classifier: Intended Audience :: Developers
Classifier: Intended Audience :: Financial and Insurance Industry
Classifier: Intended Audience :: Information Technology
Classifier: Intended Audience :: Science/Research
Classifier: Topic :: Software Development :: Libraries
Classifier: Topic :: Scientific/Engineering :: Information Analysis
Classifier: Natural Language :: English
Requires-Python: >=3.7.0,<3.10.0
License-File: LICENSE
Requires-Dist: pandas (>=1.2.4)
Requires-Dist: numpy (>=1.20.1)
Requires-Dist: ta (>=0.7.0)
Requires-Dist: scikit-learn (>=0.23.1)
Requires-Dist: matplotlib (>=3.3.4)
Requires-Dist: typing-extensions (>=3.7.4.3)
Requires-Dist: Markdown (>=3.3.4)
Requires-Dist: requests (>=2.26.0)
Provides-Extra: dev
Requires-Dist: pytest (==6.2.2) ; extra == 'dev'
Requires-Dist: sphinx (==3.5.4) ; extra == 'dev'
Requires-Dist: pdftex (==1.0.0) ; extra == 'dev'
Requires-Dist: myst-parser (==0.14.0) ; extra == 'dev'
Requires-Dist: pytest-cov (==2.12.1) ; extra == 'dev'
Requires-Dist: black (==21.6b0) ; extra == 'dev'
Requires-Dist: GitPython (>=3.1.18) ; extra == 'dev'
